{
  "color": {
    "base": {
      "brand": {
        "value": "216",
        "type": "other",
        "description": "HUE(HSL)"
      },
      "white": {
        "value": "0,0,100",
        "type": "other",
        "description": "HSL"
      },
      "success": {
        "value": "163",
        "type": "other",
        "description": "HUE(HSL)"
      },
      "warning": {
        "value": "42",
        "type": "other",
        "description": "HUE(HSL)"
      },
      "critical": {
        "value": "330",
        "type": "other",
        "description": "HUE(HSL)"
      }
    },
    "brand": {
      "primary": {
        "value": "hsl({color.base.brand},95,66)",
        "type": "color",
        "description": "based on HUE value of $base.color.brand"
      },
      "secondary": {
        "value": "hsl({color.base.brand},50,46)",
        "type": "color",
        "description": "based on HUE value of $base.color.brand"
      }
    },
    "feedback": {
      "success": {
        "value": "hsl({color.base.success},95,66)",
        "type": "color",
        "description": "based on HUE value of $base.color.success"
      }
    }
  },
  "$themes": [],
  "$metadata": {
    "tokenSetOrder": [
      "color"
    ]
  }
}